utaufile/__init__.py
utaufile/dictionary.py
utaufile/flag.py
utaufile-0.1.0.dist-info/LICENSE
utaufile-0.1.0.dist-info/METADATA
utaufile-0.1.0.dist-info/WHEEL
utaufile-0.1.0.dist-info/top_level.txt
utaufile-0.1.0.dist-info/RECORD
